modelsdoc/__init__.py
modelsdoc/constants.py
modelsdoc/utils.py
modelsdoc/wrappers.py
modelsdoc/management/__init__.py
modelsdoc/management/commands/__init__.py
modelsdoc/management/commands/listing_models.py
modelsdoc/templates/modelsdoc/models.md
modelsdoc/templates/modelsdoc/models.rst
modelsdoc/templates/modelsdoc/models.yaml
modelsdoc/templatetags/__init__.py
modelsdoc/templatetags/modelsdoc_tags.py
django_modelsdoc-0.1.11.dist-info/LICENSE.rst
django_modelsdoc-0.1.11.dist-info/METADATA
django_modelsdoc-0.1.11.dist-info/WHEEL
django_modelsdoc-0.1.11.dist-info/pbr.json
django_modelsdoc-0.1.11.dist-info/top_level.txt
django_modelsdoc-0.1.11.dist-info/RECORD
